skipgrammar/__init__.py
skipgrammar/datasets/__init__.py
skipgrammar/datasets/common.py
skipgrammar/datasets/lastfm.py
skipgrammar/datasets/movielens.py
skipgrammar/models/__init__.py
skipgrammar/models/lightning/__init__.py
skipgrammar/models/lightning/sgns.py
skipgrammar/models/sgns.py
skipgrammar-0.1.3.dist-info/LICENSE
skipgrammar-0.1.3.dist-info/WHEEL
skipgrammar-0.1.3.dist-info/METADATA
skipgrammar-0.1.3.dist-info/RECORD
