Metadata-Version: 2.1
Name: skipgrammar
Version: 0.1.3
Summary: A framework for representing sequences as embeddings.
Home-page: https://github.com/eifuentes/skipgrammar
License: MIT
Keywords: skipgram,word2vec,sequences,deep-learning,machine-learning
Author: Emmanuel Fuentes
Author-email: emmanuel.i.fuentes+pypi@gmail.com
Requires-Python: >=3.6.2,<3.10
Classifier: Development Status :: 3 - Alpha
Classifier: Environment :: Console
Classifier: Intended Audience :: Developers
Classifier: License :: OSI Approved :: MIT License
Classifier: Natural Language :: English
Classifier: Programming Language :: Python :: 3
Classifier: Programming Language :: Python :: 3.7
Classifier: Programming Language :: Python :: 3.8
Classifier: Programming Language :: Python :: 3.9
Classifier: Topic :: Scientific/Engineering :: Artificial Intelligence
Classifier: Topic :: Scientific/Engineering :: Information Analysis
Requires-Dist: numpy (>=1.17.2,<2.0.0)
Requires-Dist: pandas (>=1.1,<2.0)
Requires-Dist: pytorch-lightning (>=1,<2)
Requires-Dist: torch (>=1.4,<2.0)
Project-URL: Documentation, https://github.com/eifuentes/skipgrammar
Project-URL: Repository, https://github.com/eifuentes/skipgrammar
